{
  "0": "others",
  "1": "inform_symptoms",
  "2": "others",
  "3": "others",
  "4": "others",
  "5": "inform_medicine",
  "6": "request_inform",
  "7": "greeting",
  "8": "inform_medicine",
  "9": "others",
  "10": "others",
  "11": "others",
  "12": "others",
  "13": "inform_symptoms",
  "14": "inform_symptoms",
  "15": "inform_symptoms",
  "16": "others",
  "17": "inform_symptoms",
  "18": "others",
  "19": "others",
  "20": "others",
  "21": "request_inform",
  "22": "inform_medicine",
  "23": "others",
  "24": "request_inform",
  "25": "others",
  "26": "inform_symptoms",
  "27": "inform_symptoms",
  "28": "inform_symptoms",
  "29": "others",
  "30": "inform_symptoms",
  "31": "inform_symptoms",
  "32": "others",
  "33": "inform_symptoms",
  "34": "inform_symptoms",
  "35": "others",
  "36": "inform_symptoms",
  "37": "others",
  "38": "inform_symptoms",
  "39": "inform_symptoms",
  "40": "inform_medicine",
  "41": "request_inform",
  "42": "inform_symptoms",
  "43": "greeting",
  "44": "others",
  "45": "greeting",
  "46": "inform_symptoms",
  "47": "inform_symptoms",
  "48": "inform_symptoms",
  "49": "request_inform",
  "50": "greeting",
  "51": "request_inform",
  "52": "greeting",
  "53": "inform_medicine",
  "54": "inform_symptoms",
  "55": "others",
  "56": "others",
  "57": "others",
  "58": "others",
  "59": "inform_symptoms",
  "60": "greeting",
  "61": "others",
  "62": "request_inform",
  "63": "inform_symptoms",
  "64": "request_inform",
  "65": "others",
  "66": "others",
  "67": "greeting",
  "68": "others",
  "69": "inform_medicine",
  "70": "others",
  "71": "inform_medicine",
  "72": "others",
  "73": "others",
  "74": "others",
  "75": "inform_symptoms",
  "76": "inform_symptoms",
  "77": "others",
  "78": "others",
  "79": "others",
  "80": "inform_symptoms"
}